pycpu/__init__.py
pycpu/control.py
tests/__init__.py
tests/test_pycpu.py
PyCPU-0.0.42.dist-info/LICENSE.rst
PyCPU-0.0.42.dist-info/METADATA
PyCPU-0.0.42.dist-info/WHEEL
PyCPU-0.0.42.dist-info/top_level.txt
PyCPU-0.0.42.dist-info/RECORD
