Metadata-Version: 2.1
Name: PyCPU
Version: 0.0.42
Summary: Virtual CPUs Support For Python
Home-page: https://github.com/PyCPU/PyCPU
Author: PyCPU (https github.com scott91e1)
Author-email: 262646@195387.com
License: UNKNOWN
Platform: UNKNOWN
Classifier: Programming Language :: Python :: 3
Classifier: License :: OSI Approved :: MIT License
Classifier: Operating System :: OS Independent
Requires-Python: >=3.6
